Metadata-Version: 2.4
Name: typeagent-py
Version: 0.1.7
Summary: TypeAgent implements an agentic memory framework.
Author: Steven Lucco, Umesh Madan, Guido van Rossum
Author-email: Guido van Rossum <gvanrossum@microsoft.com>
Project-URL: Homepage, https://github.com/microsoft/TypeAgent/tree/main/python/ta
Requires-Python: <3.14,>=3.12
License-File: LICENSE
Requires-Dist: azure-identity>=1.22.0
Requires-Dist: black>=25.1.0
Requires-Dist: build>=1.2.2.post1
Requires-Dist: colorama>=0.4.6
Requires-Dist: coverage[toml]>=7.9.1
Requires-Dist: logfire>=4.1.0
Requires-Dist: mcp[cli]>=1.12.1
Requires-Dist: numpy>=2.2.6
Requires-Dist: openai>=1.81.0
Requires-Dist: opentelemetry-instrumentation-httpx>=0.57b0
Requires-Dist: pydantic>=2.11.4
Requires-Dist: pydantic-ai-slim[openai]>=0.5.0
Requires-Dist: pyright>=1.1.405
Requires-Dist: pytest>=8.3.5
Requires-Dist: pytest-asyncio>=0.26.0
Requires-Dist: pytest-mock>=3.14.0
Requires-Dist: python-dotenv>=1.1.0
Requires-Dist: typechat
Dynamic: license-file
